LICENSE
MANIFEST.in
README.rst
setup.py
django_galleries.egg-info/PKG-INFO
django_galleries.egg-info/SOURCES.txt
django_galleries.egg-info/dependency_links.txt
django_galleries.egg-info/requires.txt
django_galleries.egg-info/top_level.txt
exampleapp/__init__.py
exampleapp/admin.py
exampleapp/models.py
exampleapp/tests.py
exampleapp/views.py
galleries/__init__.py
galleries/admin.py
galleries/models.py
galleries/migrations/0001_initial.py
galleries/migrations/__init__.py
galleries/south_migrations/0001_initial.py
galleries/south_migrations/0002_auto__chg_field_imagemodel_original_image.py
galleries/south_migrations/__init__.py
galleries/static/galleries/js/admin-list-reorder.js
galleries/static/galleries/js/genericcollection.js
galleries/templates/galleries/base.html
galleries/templates/galleries/landing.html
galleries/templates/galleries/admin/edit_inline/gen_coll_tabular.html