Metadata-Version: 1.1
Name: django-galleries
Version: 1.3.0
Summary: Simple Django galleries.
Home-page: UNKNOWN
Author: Matthew Dapena-Tretter
Author-email: m@tthewwithanm.com
License: UNKNOWN
Platform: UNKNOWN
Classifier: Environment :: Web Environment
Classifier: Framework :: Django
Classifier: Intended Audience :: Developers
Classifier: License :: OSI Approved :: BSD License
Classifier: Operating System :: OS Independent
Classifier: Programming Language :: Python
Classifier: Topic :: Internet :: WWW/HTTP
